Athena_DL-0.6.dist-info/DESCRIPTION.rst
Athena_DL-0.6.dist-info/METADATA
Athena_DL-0.6.dist-info/RECORD
Athena_DL-0.6.dist-info/WHEEL
Athena_DL-0.6.dist-info/entry_points.txt
Athena_DL-0.6.dist-info/metadata.json
Athena_DL-0.6.dist-info/top_level.txt
athena_dl/__init__.py
athena_dl/athena_batch_query.py
athena_dl/athena_dl.py
