Metadata-Version: 2.0
Name: Athena-DL
Version: 0.6
Summary: command line interface to query SQL to Amazon Athena and save its results
Home-page: https://github.com/quiver/athena-dl
Author: George Yoshida
Author-email: UNKNOWN
License: UNKNOWN
Platform: UNKNOWN
Classifier: Development Status :: 3 - Alpha
Classifier: License :: OSI Approved :: MIT License
Classifier: Programming Language :: Python :: 2.7
Requires-Dist: boto3
Requires-Dist: Click
Requires-Dist: retrying
